setup.cfg
setup.py
KMlogger/__init__.py
KMlogger/kmLogger.py
KMlogger.egg-info/PKG-INFO
KMlogger.egg-info/SOURCES.txt
KMlogger.egg-info/dependency_links.txt
KMlogger.egg-info/requires.txt
KMlogger.egg-info/top_level.txt